Metadata-Version: 1.1
Name: fantail
Version: 0.6.10
Summary: Lightweight Python CLI framework
Home-page: https://gitlab.com/mf42/fantail
Author: Mark Fiers
Author-email: mark.fiers.42@gmail.com
License: UNKNOWN
Platform: UNKNOWN
Classifier: Development Status :: 4 - Beta
Classifier: Environment :: Console
Classifier: Intended Audience :: Developers
Classifier: Operating System :: OS Independent
Classifier: Programming Language :: Python :: 3
Classifier: Programming Language :: Python :: 3.6
Classifier: Programming Language :: Python :: 3.7
